mapdb.py
mapdb-0.0.1.dist-info/METADATA
mapdb-0.0.1.dist-info/WHEEL
mapdb-0.0.1.dist-info/entry_points.txt
mapdb-0.0.1.dist-info/top_level.txt
mapdb-0.0.1.dist-info/RECORD
