Metadata-Version: 2.1
Name: mapdb
Version: 0.0.1
Summary: 简单的kv数据操作工具。
Home-page: https://github.com/kancyframework/python-plugins/tree/main/mapdb
Author: kancy
Author-email: 793272861@qq.com
License: MIT
Platform: UNKNOWN
Classifier: License :: OSI Approved :: MIT License
Classifier: Programming Language :: Python
Classifier: Programming Language :: Python :: 3
Classifier: Programming Language :: Python :: 3.6
Classifier: Programming Language :: Python :: Implementation :: CPython
Classifier: Programming Language :: Python :: Implementation :: PyPy
Requires-Python: >=3
Requires-Dist: dber
Provides-Extra: mysql_feature
Requires-Dist: pymysql ; extra == 'mysql_feature'
